chiklisp_stdlib/__init__.py
chiklisp_stdlib/nightly/curry-and-treehash.clib
chiklisp_stdlib/nightly/merkle_utils.clib
chiklisp_stdlib/nightly/signing.clinc
chiklisp_stdlib/nightly/utility_macros.clib
chiklisp_stdlib/stable/condition_codes.clib
chiklisp_stdlib/stable/curry.clib
chiklisp_stdlib/stable/sha256tree.clib
chiklisp_stdlib-0.1.1.dist-info/LICENSE
chiklisp_stdlib-0.1.1.dist-info/METADATA
chiklisp_stdlib-0.1.1.dist-info/WHEEL
chiklisp_stdlib-0.1.1.dist-info/top_level.txt
chiklisp_stdlib-0.1.1.dist-info/RECORD
