Metadata-Version: 2.1
Name: chiklisp-stdlib
Version: 0.1.1
Summary: Chiklisp `.clib` standard library files
Author-email: Richard Kiss <him@richardkiss.com>
License: Copyright 2023 by Richard Kiss
License-File: LICENSE
Requires-Dist: importlib-resources
Provides-Extra: dev
Requires-Dist: pytest ; extra == 'dev'
Requires-Dist: chik-base ; extra == 'dev'
Requires-Dist: chiklisp-puzzles ; extra == 'dev'
Requires-Dist: klvm-tools-rs ; extra == 'dev'
